msmcp_azure/__init__.py
msmcp_azure/bin/Azure.Mcp.Tools.AzureMigrate.xml
msmcp_azure/bin/appsettings.json
msmcp_azure/bin/azmcp
msmcp_azure-2.0.0b15.dist-info/METADATA
msmcp_azure-2.0.0b15.dist-info/WHEEL
msmcp_azure-2.0.0b15.dist-info/entry_points.txt
msmcp_azure-2.0.0b15.dist-info/licenses/LICENSE
msmcp_azure-2.0.0b15.dist-info/licenses/NOTICE.txt
msmcp_azure-2.0.0b15.dist-info/RECORD
